wenxin/wenxin.py
Wenxin-1.1.4.dist-info/LICENSE
Wenxin-1.1.4.dist-info/METADATA
Wenxin-1.1.4.dist-info/WHEEL
Wenxin-1.1.4.dist-info/top_level.txt
Wenxin-1.1.4.dist-info/RECORD
