Metadata-Version: 2.1
Name: Wenxin
Version: 1.1.4
Summary: a reverse engineering of ERNIEBot
Home-page: https://github.com/Soulter/ERNIEBot
Author: Soulter
Author-email: 905617992@qq.com
License: GNU Affero General Public License v3.0
Project-URL: Bug Report, https://github.com/Soulter/ERNIEBot/issues
Classifier: License :: OSI Approved :: GNU General Public License v3 (GPLv3)
Classifier: Intended Audience :: Developers
Classifier: Intended Audience :: End Users/Desktop
Classifier: Natural Language :: English
Classifier: Topic :: Software Development :: Libraries :: Python Modules
Classifier: Programming Language :: Python :: 3 :: Only
Classifier: Programming Language :: Python :: 3.9
Classifier: Programming Language :: Python :: 3.10
Classifier: Programming Language :: Python :: 3.11
License-File: LICENSE
Requires-Dist: selenium (==4.8.2)
Requires-Dist: browsermob-proxy (==0.8.0)
Requires-Dist: requests
